Metadata-Version: 2.1
Name: tecoroute-proxy
Version: 0.2.0
Summary: Proxy for easy authentication to the TecoRoute service.
Home-page: https://tecoroute-proxy.readthedocs.io
Author: Petr Czepiec
Author-email: petr@czepiec.me
Maintainer: Petr Czepiec
Maintainer-email: petr@czepiec.me
License: MIT
Project-URL: Documentation, https://tecoroute-proxy.readthedocs.io/
Project-URL: Source, https://github.com/czetech/tecoroute-proxy
Project-URL: Tracker, https://github.com/czetech/tecoroute-proxy/issues
Project-URL: Changelog, https://github.com/czetech/tecoroute-proxy/blob/master/CHANGELOG.md
Keywords: authentication,proxy,tecoroute
Platform: UNKNOWN
Classifier: Development Status :: 5 - Production/Stable
Classifier: Environment :: Web Environment
Classifier: Framework :: AsyncIO
Classifier: Intended Audience :: Information Technology
Classifier: License :: OSI Approved :: MIT License
Classifier: Natural Language :: English
Classifier: Operating System :: OS Independent
Classifier: Programming Language :: Python :: 3.6
Classifier: Programming Language :: Python :: 3.7
Classifier: Programming Language :: Python :: 3.8
Classifier: Programming Language :: Python :: 3.9
Classifier: Programming Language :: Python :: 3.10
Classifier: Topic :: Internet :: Proxy Servers
Classifier: Topic :: Internet :: WWW/HTTP
Requires-Python: >=3.6
License-File: LICENSE
